Flask_Login_Multi-0.1.1.dist-info/METADATA
Flask_Login_Multi-0.1.1.dist-info/RECORD
Flask_Login_Multi-0.1.1.dist-info/WHEEL
Flask_Login_Multi-0.1.1.dist-info/top_level.txt
flask_login_multi/__init__.py
flask_login_multi/login_manager.py
