Metadata-Version: 2.1
Name: Flask-Login-Multi
Version: 0.1.1
Summary: Flask-Login with multiple models
Home-page: https://github.com/siaoynli/flask_login_multi
Author: siaoynli
Author-email: lixiaoyun2010@gmail.com
License: UNKNOWN
Platform: UNKNOWN
Classifier: Programming Language :: Python :: 3
Classifier: License :: OSI Approved :: MIT License
Classifier: Operating System :: OS Independent
